optimate/__init__.py
optimate/_pytesttester.py
optimate/cli.py
optimate/version.py
optimate/tests/__init__.py
optimate/tests/test_utilities/__init__.py
optimate/tests/test_utilities/test_forecastingMetrics.py
optimate/tests/test_utilities/test_linearInterpolation.py
optimate/tests/test_utilities/test_qualityOfFit.py
optimate/utilities/__init__.py
optimate/utilities/commandLineInterface.py
optimate/utilities/dataPointClass.py
optimate/utilities/errorClass.py
optimate/utilities/experimentSorter.py
optimate/utilities/forecastingMetrics.py
optimate/utilities/linearInterpolation.py
optimate/utilities/qualityOfFit.py
optimate/utilities/tracebackExceptions.py
optimate-0.0.1.data/scripts/optimate
optimate-0.0.1.dist-info/LICENSE.md
optimate-0.0.1.dist-info/METADATA
optimate-0.0.1.dist-info/WHEEL
optimate-0.0.1.dist-info/top_level.txt
optimate-0.0.1.dist-info/RECORD
