Metadata-Version: 2.1
Name: optimate
Version: 0.0.1
Summary: optimate - parameter optimizer for different material models
Home-page: 
Author: Muhammad Mohsin Khan
Author-email: mohsin.khan1@outlook.com
License: MIT
Keywords: optimizer minimizer parameters
Platform: Linux
Platform: Mac OS-X
Platform: Unix
Classifier: Development Status :: 1 - Planning
Classifier: Environment :: Console
Classifier: Intended Audience :: Education
Classifier: Intended Audience :: Science/Research
Classifier: License :: OSI Approved :: MIT License
Classifier: Natural Language :: English
Classifier: Operating System :: POSIX :: Linux
Classifier: Operating System :: MacOS
Classifier: Programming Language :: Python :: 3.8
Classifier: Topic :: Scientific/Engineering
Requires-Python: >=3.8
License-File: LICENSE.md
Requires-Dist: pytest (>=7.1.1)
Requires-Dist: scipy (>=1.8.0)
Requires-Dist: numpy (>=1.21.5)
Requires-Dist: matplotlib (>=3.5.1)
Requires-Dist: pandas (>=1.4.1)
